autosink_model_evaluation/__init__.py
autosink_model_evaluation/subpackage/__init__.py
autosink_model_evaluation/subpackage/hello.py
autosink_model_evaluation/subpackage/test_hello.py
autosink_model_evaluation-0.1.0.dist-info/WHEEL
autosink_model_evaluation-0.1.0.dist-info/METADATA
autosink_model_evaluation-0.1.0.dist-info/RECORD
